{"z": ["P[DX]*", "[KU]*.*[JR]*[CJ]*.*Q.*", ".*C[DX]*", "[GQ]*[NT]*.*[JL]*[JR]*", "[XZ]*.*[IX]*U.*[IU]*G", ".*LOT.*N[IJ]*.*", "W[UW]*[TU]*.*R.*[TW]*[KU]*.*", "T[GO]*.*U.*[KR]*.*JP", ".*O[IO]*.*L[LO]*.*O", "[OW]*[IJ]*T.*[OX]*", "RI[DZ]*[PR]*.*U", ".*[TX]*.*RU.*", "U.*N[LW]*[PQ]*"], "y": ["W[NQ]*.*[PT]*", ".*[UW]*[GO]*OI[TX]*", "[XZ]*L.*[IO]*[OW]*.*", "[GQ]*.*OU.*", ".*[IX]*.*L[IJ]*[PR]*R", "[KU]*.*[NT]*UT[TU]*[KR]*[LO]*TU", ".*", "W[JR]*.*R.*U", "[PW]*[CJ]*.*[OX]*", "T.*C[JL]*[IU]*N[TW]*JO", "GQ[DY]*[IJ]*[KU]*P", ".*[JR]*G.*", ".*[IT]*JP"], "x": ["U[PQ]*QX[IO]*", "W.*L[UW]*", "[PW]*[JR]*.*[NT]*[IX]*O[GO]*", "T[CJ]*.*U.*O", "G.*TU[IO]*", "QC.*[TU]*.*[OW]*I", ".*[JL]*.*[KR]*L[TX]*", "[IU]*R.*[LO]*[IJ]*.*", "[JR]*N.*T[PR]*.*", ".*G[IJ]*[TW]*.*R", "[JK]*.*[KU]*J.*U", "[PR]*.*PO[OX]*U.*", "Y[KP]*[LP]*.*[LR]*"], "size": 13, "name": "1389910034008869"}